wsrepl/MessageHandler.py
wsrepl/Ping0x1Thread.py
wsrepl/PingThread.py
wsrepl/Plugin.py
wsrepl/WSMessage.py
wsrepl/WebsocketConnection.py
wsrepl/__init__.py
wsrepl/__main__.py
wsrepl/app.css
wsrepl/app.py
wsrepl/cli.py
wsrepl/constants.py
wsrepl/log.py
wsrepl/utils.py
wsrepl/widgets/CopyButton.py
wsrepl/widgets/DirectionSign.py
wsrepl/widgets/FormattedMessage.py
wsrepl/widgets/History.py
wsrepl/widgets/HistoryIndex.py
wsrepl/widgets/HistoryRow.py
wsrepl/widgets/Parent.py
wsrepl/widgets/__init__.py
wsrepl-0.2.0.dist-info/METADATA
wsrepl-0.2.0.dist-info/WHEEL
wsrepl-0.2.0.dist-info/entry_points.txt
wsrepl-0.2.0.dist-info/RECORD
