Metadata-Version: 2.1
Name: wsrepl
Version: 0.2.0
Summary: Websocket REPL for pentesters
Home-page: https://github.com/doyensec/wsrepl
License: MIT
Keywords: websocket,pentesting
Author: Andrew Konstantinov
Author-email: 105389353+execveat@users.noreply.github.com
Requires-Python: >3.10,<4.0
Classifier: License :: OSI Approved :: MIT License
Classifier: Programming Language :: Python :: 3
Classifier: Programming Language :: Python :: 3.11
Requires-Dist: pyperclip (>=1.8.2,<2.0.0)
Requires-Dist: rich (>=13.4.2,<14.0.0)
Requires-Dist: textual (>=0.30.0,<0.31.0)
Requires-Dist: websocket-client (>=1.5.2,<2.0.0)
